medialoopster/__init__.py
medialoopster/api.py
medialoopster/exceptions.py
medialoopster/schemas.py
medialoopster-0.3.1.dist-info/METADATA
medialoopster-0.3.1.dist-info/WHEEL
medialoopster-0.3.1.dist-info/top_level.txt
medialoopster-0.3.1.dist-info/RECORD
