Metadata-Version: 2.4
Name: medialoopster
Version: 0.3.1
Summary: medialoopster API wrapper for Python
Author-email: Stéphane Ludwig <stephane.ludwig@swr.de>
License: MIT
Project-URL: homepage, https://gitlab.com/medialoopster/medialoopster-python
Classifier: Programming Language :: Python :: 3
Classifier: License :: OSI Approved :: MIT License
Classifier: Operating System :: OS Independent
Requires-Dist: requests<3
Requires-Dist: pydantic>2
